cistell/__init__.py
cistell/base.py
cistell/constants.py
cistell/defaults.py
cistell/exceptions.py
cistell/field.py
cistell/root.py
cistell/util_files.py
cistell-0.0.7.dist-info/LICENSE
cistell-0.0.7.dist-info/METADATA
cistell-0.0.7.dist-info/WHEEL
cistell-0.0.7.dist-info/RECORD
