Metadata-Version: 2.1
Name: cistell
Version: 0.0.7
Summary: Configuration library for pynenc and piceli projects
Home-page: https://cistell.pynenc.org
License: MIT
Author: Jose Diaz
Requires-Python: >=3.11.6
Classifier: Development Status :: 3 - Alpha
Classifier: Intended Audience :: Developers
Classifier: License :: OSI Approved :: MIT License
Classifier: Programming Language :: Python :: 3
Classifier: Programming Language :: Python :: 3.12
Classifier: Programming Language :: Python :: 3.11
Classifier: Topic :: Software Development :: Libraries :: Python Modules
Requires-Dist: pyyaml (>=6.0.1,<7.0.0)
Requires-Dist: typing-extensions (>=4.9.0,<5.0.0)
Project-URL: Documentation, https://docs.cistell.pynenc.org
Project-URL: Repository, https://github.com/pynenc/cistell
